source_braintree/__init__.py
source_braintree/manifest.yaml
source_braintree/run.py
source_braintree/schemas/__init__.py
source_braintree/schemas/cards.py
source_braintree/schemas/common.py
source_braintree/schemas/customer.py
source_braintree/schemas/discount.py
source_braintree/schemas/dispute.py
source_braintree/schemas/merchant_account.py
source_braintree/schemas/plan.py
source_braintree/schemas/subscription.py
source_braintree/schemas/transaction.py
source_braintree/source.py
airbyte_source_braintree-0.3.28.dist-info/METADATA
airbyte_source_braintree-0.3.28.dist-info/WHEEL
airbyte_source_braintree-0.3.28.dist-info/entry_points.txt
airbyte_source_braintree-0.3.28.dist-info/RECORD
