Metadata-Version: 2.3
Name: airbyte-source-braintree
Version: 0.3.28
Summary: Source implementation for Braintree.
License: MIT
Author: Airbyte
Author-email: contact@airbyte.io
Requires-Python: >=3.9,<3.12
Classifier: License :: OSI Approved :: MIT License
Classifier: Programming Language :: Python :: 3
Classifier: Programming Language :: Python :: 3.9
Classifier: Programming Language :: Python :: 3.10
Classifier: Programming Language :: Python :: 3.11
Requires-Dist: airbyte-cdk (>=0.50,<0.51)
Requires-Dist: braintree (>=4.28.0,<5.0.0)
Project-URL: Documentation, https://docs.airbyte.com/integrations/sources/braintree
Project-URL: Homepage, https://airbyte.com
Project-URL: Repository, https://github.com/airbytehq/airbyte
